{
    "wallpaper": "/home/crystal/Pictures/Wallpapers/E8yf4NSVcAE9YeU-8FCFB.png",
    "alpha": "100",
    "special": {
        "background": "#0d0d0f",
        "foreground": "#b89b92",
        "cursor": "#b89b92"
    },
    "colors": {
        "color0": "#0d0d0f",
        "color1": "#522B23",
        "color2": "#6C3727",
        "color3": "#7A4432",
        "color4": "#324849",
        "color5": "#394F53",
        "color6": "#834733",
        "color7": "#b89b92",
        "color8": "#806c66",
        "color9": "#522B23",
        "color10": "#6C3727",
        "color11": "#7A4432",
        "color12": "#324849",
        "color13": "#394F53",
        "color14": "#834733",
        "color15": "#b89b92"
    }
}